{
  "firstLayout": "",
  "gdVersion": {
    "build": 213,
    "major": 5,
    "minor": 4,
    "revision": 0
  },
  "properties": {
    "adaptGameResolutionAtRuntime": true,
    "antialiasingMode": "MSAA",
    "antialisingEnabledOnMobile": false,
    "folderProject": false,
    "orientation": "landscape",
    "packageName": "com.example.gamename",
    "pixelsRounding": true,
    "projectUuid": "15d23f70-df24-467c-bb9d-62d2f0476e35",
    "scaleMode": "nearest",
    "sizeOnStartupMode": "adaptWidth",
    "templateSlug": "",
    "useExternalSourceFiles": false,
    "version": "1.0.0",
    "name": "Proyecto Grupo 5",
    "description": "",
    "author": "",
    "windowWidth": 1280,
    "windowHeight": 720,
    "latestCompilationDirectory": "",
    "maxFPS": 60,
    "minFPS": 20,
    "verticalSync": false,
    "platformSpecificAssets": {},
    "loadingScreen": {
      "backgroundColor": 0,
      "backgroundFadeInDuration": 0.2,
      "backgroundImageResourceName": "",
      "gdevelopLogoStyle": "light",
      "logoAndProgressFadeInDuration": 0.2,
      "logoAndProgressLogoFadeInDelay": 0,
      "minDuration": 1.5,
      "progressBarColor": 16777215,
      "progressBarHeight": 20,
      "progressBarMaxWidth": 200,
      "progressBarMinWidth": 40,
      "progressBarWidthPercent": 30,
      "showGDevelopSplash": true,
      "showProgressBar": true
    },
    "watermark": {
      "placement": "bottom-left",
      "showWatermark": true
    },
    "authorIds": [],
    "authorUsernames": [],
    "categories": [],
    "playableDevices": [],
    "extensionProperties": [],
    "platforms": [
      {
        "name": "GDevelop JS platform"
      }
    ],
    "currentPlatform": "GDevelop JS platform"
  },
  "resources": {
    "resources": [
      {
        "alwaysLoaded": false,
        "file": "assets/NewSprite.png",
        "kind": "image",
        "metadata": "{\"extension\":\".png\"}",
        "name": "NewSprite",
        "smoothed": false,
        "userAdded": true
      },
      {
        "alwaysLoaded": false,
        "file": "assets/NewSprite2.png",
        "kind": "image",
        "metadata": "{\"extension\":\".png\"}",
        "name": "NewSprite2",
        "smoothed": false,
        "userAdded": false
      },
      {
        "alwaysLoaded": false,
        "file": "assets/NewSprite3.png",
        "kind": "image",
        "metadata": "{\"extension\":\".png\"}",
        "name": "NewSprite3",
        "smoothed": false,
        "userAdded": false
      },
      {
        "alwaysLoaded": false,
        "file": "assets/nivel1.jpg.png",
        "kind": "image",
        "metadata": "",
        "name": "nivel1.jpg.png",
        "smoothed": false,
        "userAdded": false,
        "origin": {
          "identifier": "https://project-resources.gdevelop.io/c247579e-f830-43be-ba0d-7bcb1ca8bf7f/resources/4b536852349fae29c9ffe59b4c68575ffcbceafb19046e1cda9a8648f09cd83f-nivel1.jpg.png",
          "name": "cloud-project-resource"
        }
      },
      {
        "alwaysLoaded": false,
        "file": "assets/NewSprite4.png",
        "kind": "image",
        "metadata": "{\"extension\":\".png\"}",
        "name": "NewSprite4",
        "smoothed": false,
        "userAdded": true
      },
      {
        "alwaysLoaded": false,
        "file": "assets/fondo.png",
        "kind": "image",
        "metadata": "{\"extension\":\".png\"}",
        "name": "fondo",
        "smoothed": false,
        "userAdded": true
      },
      {
        "alwaysLoaded": false,
        "file": "assets/fondo2.png",
        "kind": "image",
        "metadata": "{\"extension\":\".png\"}",
        "name": "fondo2",
        "smoothed": false,
        "userAdded": false
      },
      {
        "alwaysLoaded": false,
        "file": "assets/marte.png",
        "kind": "image",
        "metadata": "{\"extension\":\".png\"}",
        "name": "marte",
        "smoothed": false,
        "userAdded": false
      },
      {
        "alwaysLoaded": false,
        "file": "assets/cohete.png",
        "kind": "image",
        "metadata": "",
        "name": "cohete.png",
        "smoothed": false,
        "userAdded": true,
        "origin": {
          "identifier": "https://project-resources.gdevelop.io/c247579e-f830-43be-ba0d-7bcb1ca8bf7f/resources/59a93928fdf5edeb25daba389be29d0cd979218bc33f556e896b072d4c1f8acf-cohete.png",
          "name": "cloud-project-resource"
        }
      },
      {
        "alwaysLoaded": false,
        "file": "assets/tarjeta.png.png",
        "kind": "image",
        "metadata": "{\"extension\":\".png\"}",
        "name": "tarjeta.png",
        "smoothed": false,
        "userAdded": true,
        "origin": {
          "identifier": "https://project-resources.gdevelop.io/c247579e-f830-43be-ba0d-7bcb1ca8bf7f/resources/1ec9a36a71c9aeff5d25a3ac1413812ad85d631e3a38b3cb2af9226a72c495b7-tarjeta.png",
          "name": "cloud-project-resource"
        }
      },
      {
        "alwaysLoaded": false,
        "file": "assets/piedra.png",
        "kind": "image",
        "metadata": "",
        "name": "piedra.png",
        "smoothed": false,
        "userAdded": false,
        "origin": {
          "identifier": "https://project-resources.gdevelop.io/c247579e-f830-43be-ba0d-7bcb1ca8bf7f/resources/fe773ed5cfa35ac1962b4bdb23d1004989912efd13e7fe561bef77e960d63801-piedra.png",
          "name": "cloud-project-resource"
        }
      },
      {
        "alwaysLoaded": false,
        "file": "assets/NewSprite7.png",
        "kind": "image",
        "metadata": "{\"extension\":\".png\"}",
        "name": "NewSprite7",
        "smoothed": false,
        "userAdded": false
      },
      {
        "alwaysLoaded": false,
        "file": "assets/NewSprite8.png",
        "kind": "image",
        "metadata": "{\"extension\":\".png\"}",
        "name": "NewSprite8",
        "smoothed": false,
        "userAdded": false
      },
      {
        "alwaysLoaded": false,
        "file": "assets/NewSprite9.png",
        "kind": "image",
        "metadata": "{\"extension\":\".png\"}",
        "name": "NewSprite9",
        "smoothed": false,
        "userAdded": true
      },
      {
        "alwaysLoaded": false,
        "file": "assets/tierra.png",
        "kind": "image",
        "metadata": "{\"extension\":\".png\"}",
        "name": "tierra",
        "smoothed": false,
        "userAdded": true
      },
      {
        "file": "assets/agarrar.mp3.wav",
        "kind": "audio",
        "metadata": "",
        "name": "agarrar.mp3.wav",
        "preloadAsMusic": false,
        "preloadAsSound": false,
        "preloadInCache": false,
        "userAdded": true,
        "origin": {
          "identifier": "https://project-resources.gdevelop.io/c247579e-f830-43be-ba0d-7bcb1ca8bf7f/resources/0ea650ea4bc4fe8fd768ed37e55f8b6aec5e0423391247f8eadf3cb537caf2f8-agarrar.mp3.wav",
          "name": "cloud-project-resource"
        }
      },
      {
        "file": "assets/salto.mp3.wav",
        "kind": "audio",
        "metadata": "",
        "name": "salto.mp3.wav",
        "preloadAsMusic": false,
        "preloadAsSound": false,
        "preloadInCache": false,
        "userAdded": true,
        "origin": {
          "identifier": "https://project-resources.gdevelop.io/c247579e-f830-43be-ba0d-7bcb1ca8bf7f/resources/dbe5c9807adb82215361347b7573d35b33bca353b84dbd5c0609ed11019b9471-salto.mp3.wav",
          "name": "cloud-project-resource"
        }
      },
      {
        "alwaysLoaded": false,
        "file": "assets/tarjeta.png",
        "kind": "image",
        "metadata": "{\"extension\":\".png\"}",
        "name": "tarjeta",
        "smoothed": false,
        "userAdded": false
      },
      {
        "alwaysLoaded": false,
        "file": "assets/dentro del cohete.png",
        "kind": "image",
        "metadata": "{\"extension\":\".png\"}",
        "name": "dentro del cohete",
        "smoothed": false,
        "userAdded": false
      },
      {
        "alwaysLoaded": false,
        "file": "assets/NewSprite10.png",
        "kind": "image",
        "metadata": "{\"extension\":\".png\"}",
        "name": "NewSprite10",
        "smoothed": false,
        "userAdded": false
      },
      {
        "alwaysLoaded": false,
        "file": "assets/dentro del cohete2.png",
        "kind": "image",
        "metadata": "{\"extension\":\".png\"}",
        "name": "dentro del cohete2",
        "smoothed": false,
        "userAdded": true
      }
    ],
    "resourceFolders": []
  },
  "objects": [
    {
      "adaptCollisionMaskAutomatically": true,
      "assetStoreId": "",
      "name": "tierra_inicio",
      "type": "Sprite",
      "updateIfNotVisible": false,
      "variables": [],
      "effects": [],
      "behaviors": [],
      "animations": [
        {
          "name": "tierra d4esde afurera",
          "useMultipleDirections": false,
          "directions": [
            {
              "looping": false,
              "timeBetweenFrames": 0.08,
              "sprites": [
                {
                  "hasCustomCollisionMask": true,
                  "image": "nivel1.jpg.png",
                  "points": [],
                  "originPoint": {
                    "name": "origine",
                    "x": 0,
                    "y": 0
                  },
                  "centerPoint": {
                    "automatic": true,
                    "name": "centre",
                    "x": 0,
                    "y": 0
                  },
                  "customCollisionMask": [
                    [
                      {
                        "x": 0,
                        "y": 0
                      },
                      {
                        "x": 2000,
                        "y": 0
                      },
                      {
                        "x": 2000,
                        "y": 1500
                      },
                      {
                        "x": 0,
                        "y": 1500
                      }
                    ]
                  ]
                }
              ]
            }
          ]
        }
      ]
    },
    {
      "adaptCollisionMaskAutomatically": true,
      "assetStoreId": "",
      "name": "Laika",
      "type": "Sprite",
      "updateIfNotVisible": false,
      "variables": [],
      "effects": [],
      "behaviors": [
        {
          "name": "PlatformerObject",
          "type": "PlatformBehavior::PlatformerObjectBehavior",
          "acceleration": 1500,
          "deceleration": 1500,
          "gravity": 1000,
          "jumpSpeed": 700,
          "jumpSustainTime": 0.2,
          "maxSpeed": 250,
          "canGoDownFromJumpthru": true,
          "canGrabPlatforms": false,
          "canGrabWithoutMoving": true,
          "ignoreDefaultControls": false,
          "ladderClimbingSpeed": 150,
          "maxFallingSpeed": 700,
          "slopeMaxAngle": 60,
          "useLegacyTrajectory": false,
          "xGrabTolerance": 10,
          "yGrabOffset": 0
        },
        {
          "name": "TopDownMovement",
          "type": "TopDownMovementBehavior::TopDownMovementBehavior",
          "acceleration": 900,
          "deceleration": 1000,
          "maxSpeed": 300,
          "allowDiagonals": false,
          "angleOffset": 0,
          "angularMaxSpeed": 180,
          "customIsometryAngle": 30,
          "ignoreDefaultControls": false,
          "movementAngleOffset": 0,
          "rotateObject": false,
          "viewpoint": "TopDown"
        }
      ],
      "animations": [
        {
          "name": "NewSprite",
          "useMultipleDirections": false,
          "directions": [
            {
              "looping": false,
              "metadata": "{\"pskl\":{}}",
              "timeBetweenFrames": 0.08,
              "sprites": [
                {
                  "hasCustomCollisionMask": true,
                  "image": "NewSprite",
                  "points": [],
                  "originPoint": {
                    "name": "origine",
                    "x": 0,
                    "y": 0
                  },
                  "centerPoint": {
                    "automatic": true,
                    "name": "centre",
                    "x": 0,
                    "y": 0
                  },
                  "customCollisionMask": [
                    [
                      {
                        "x": 16,
                        "y": 8
                      },
                      {
                        "x": 30,
                        "y": 8
                      },
                      {
                        "x": 30,
                        "y": 18
                      },
                      {
                        "x": 16,
                        "y": 18
                      }
                    ]
                  ]
                }
              ]
            }
          ]
        }
      ]
    },
    {
      "adaptCollisionMaskAutomatically": true,
      "assetStoreId": "",
      "name": "Enemigo",
      "type": "Sprite",
      "updateIfNotVisible": false,
      "variables": [],
      "effects": [],
      "behaviors": [],
      "animations": [
        {
          "name": "NewSprite2",
          "useMultipleDirections": false,
          "directions": [
            {
              "looping": false,
              "metadata": "{\"pskl\":{}}",
              "timeBetweenFrames": 0.08,
              "sprites": [
                {
                  "hasCustomCollisionMask": true,
                  "image": "NewSprite2",
                  "points": [],
                  "originPoint": {
                    "name": "origine",
                    "x": 0,
                    "y": 0
                  },
                  "centerPoint": {
                    "automatic": true,
                    "name": "centre",
                    "x": 0,
                    "y": 0
                  },
                  "customCollisionMask": [
                    [
                      {
                        "x": 23,
                        "y": 20
                      },
                      {
                        "x": 45,
                        "y": 20
                      },
                      {
                        "x": 45,
                        "y": 58
                      },
                      {
                        "x": 23,
                        "y": 58
                      }
                    ]
                  ]
                }
              ]
            }
          ]
        }
      ]
    },
    {
      "adaptCollisionMaskAutomatically": true,
      "assetStoreId": "",
      "name": "Estrella",
      "type": "Sprite",
      "updateIfNotVisible": false,
      "variables": [],
      "effects": [],
      "behaviors": [],
      "animations": [
        {
          "name": "NewSprite3",
          "useMultipleDirections": false,
          "directions": [
            {
              "looping": false,
              "metadata": "{\"pskl\":{}}",
              "timeBetweenFrames": 0.08,
              "sprites": [
                {
                  "hasCustomCollisionMask": true,
                  "image": "NewSprite3",
                  "points": [],
                  "originPoint": {
                    "name": "origine",
                    "x": 0,
                    "y": 0
                  },
                  "centerPoint": {
                    "automatic": true,
                    "name": "centre",
                    "x": 0,
                    "y": 0
                  },
                  "customCollisionMask": [
                    [
                      {
                        "x": 23,
                        "y": 16
                      },
                      {
                        "x": 38,
                        "y": 16
                      },
                      {
                        "x": 38,
                        "y": 31
                      },
                      {
                        "x": 23,
                        "y": 31
                      }
                    ]
                  ]
                }
              ]
            }
          ]
        }
      ]
    },
    {
      "adaptCollisionMaskAutomatically": true,
      "assetStoreId": "",
      "name": "cohete",
      "type": "Sprite",
      "updateIfNotVisible": false,
      "variables": [],
      "effects": [],
      "behaviors": [],
      "animations": [
        {
          "name": "",
          "useMultipleDirections": false,
          "directions": [
            {
              "looping": false,
              "timeBetweenFrames": 0.08,
              "sprites": [
                {
                  "hasCustomCollisionMask": true,
                  "image": "cohete.png",
                  "points": [],
                  "originPoint": {
                    "name": "origine",
                    "x": 0,
                    "y": 0
                  },
                  "centerPoint": {
                    "automatic": true,
                    "name": "centre",
                    "x": 0,
                    "y": 0
                  },
                  "customCollisionMask": [
                    [
                      {
                        "x": 42,
                        "y": 27
                      },
                      {
                        "x": 63,
                        "y": 27
                      },
                      {
                        "x": 63,
                        "y": 66
                      },
                      {
                        "x": 42,
                        "y": 66
                      }
                    ]
                  ]
                }
              ]
            }
          ]
        }
      ]
    },
    {
      "adaptCollisionMaskAutomatically": true,
      "assetStoreId": "",
      "name": "tarjeta",
      "type": "Sprite",
      "updateIfNotVisible": false,
      "variables": [],
      "effects": [],
      "behaviors": [],
      "animations": [
        {
          "name": "tarjeta",
          "useMultipleDirections": false,
          "directions": [
            {
              "looping": false,
              "metadata": "{\"pskl\":{}}",
              "timeBetweenFrames": 0.08,
              "sprites": [
                {
                  "hasCustomCollisionMask": true,
                  "image": "tarjeta",
                  "points": [],
                  "originPoint": {
                    "name": "origine",
                    "x": 0,
                    "y": 0
                  },
                  "centerPoint": {
                    "automatic": true,
                    "name": "centre",
                    "x": 0,
                    "y": 0
                  },
                  "customCollisionMask": [
                    [
                      {
                        "x": 30,
                        "y": 30
                      },
                      {
                        "x": 63,
                        "y": 30
                      },
                      {
                        "x": 63,
                        "y": 48
                      },
                      {
                        "x": 30,
                        "y": 48
                      }
                    ]
                  ]
                }
              ]
            }
          ]
        }
      ]
    },
    {
      "adaptCollisionMaskAutomatically": true,
      "assetStoreId": "",
      "name": "piedra",
      "type": "Sprite",
      "updateIfNotVisible": false,
      "variables": [],
      "effects": [],
      "behaviors": [],
      "animations": [
        {
          "name": "",
          "useMultipleDirections": false,
          "directions": [
            {
              "looping": false,
              "timeBetweenFrames": 0.08,
              "sprites": [
                {
                  "hasCustomCollisionMask": true,
                  "image": "piedra.png",
                  "points": [],
                  "originPoint": {
                    "name": "origine",
                    "x": 0,
                    "y": 0
                  },
                  "centerPoint": {
                    "automatic": true,
                    "name": "centre",
                    "x": 0,
                    "y": 0
                  },
                  "customCollisionMask": [
                    [
                      {
                        "x": 36,
                        "y": 33
                      },
                      {
                        "x": 72,
                        "y": 33
                      },
                      {
                        "x": 72,
                        "y": 60
                      },
                      {
                        "x": 36,
                        "y": 60
                      }
                    ]
                  ]
                }
              ]
            }
          ]
        }
      ]
    },
    {
      "adaptCollisionMaskAutomatically": true,
      "assetStoreId": "",
      "name": "laikanav",
      "type": "Sprite",
      "updateIfNotVisible": false,
      "variables": [],
      "effects": [],
      "behaviors": [],
      "animations": [
        {
          "name": "NewSprite4",
          "useMultipleDirections": false,
          "directions": [
            {
              "looping": false,
              "metadata": "{\"pskl\":{}}",
              "timeBetweenFrames": 0.08,
              "sprites": [
                {
                  "hasCustomCollisionMask": true,
                  "image": "NewSprite4",
                  "points": [],
                  "originPoint": {
                    "name": "origine",
                    "x": 0,
                    "y": 0
                  },
                  "centerPoint": {
                    "automatic": true,
                    "name": "centre",
                    "x": 0,
                    "y": 0
                  },
                  "customCollisionMask": [
                    [
                      {
                        "x": 8,
                        "y": 7
                      },
                      {
                        "x": 54,
                        "y": 7
                      },
                      {
                        "x": 54,
                        "y": 42
                      },
                      {
                        "x": 8,
                        "y": 42
                      }
                    ]
                  ]
                }
              ]
            }
          ]
        }
      ]
    },
    {
      "adaptCollisionMaskAutomatically": true,
      "assetStoreId": "",
      "name": "text",
      "type": "Sprite",
      "updateIfNotVisible": false,
      "variables": [],
      "effects": [],
      "behaviors": [],
      "animations": [
        {
          "name": "NewSprite7",
          "useMultipleDirections": false,
          "directions": [
            {
              "looping": false,
              "metadata": "{\"pskl\":{}}",
              "timeBetweenFrames": 0.08,
              "sprites": [
                {
                  "hasCustomCollisionMask": true,
                  "image": "NewSprite9",
                  "points": [],
                  "originPoint": {
                    "name": "origine",
                    "x": 0,
                    "y": 0
                  },
                  "centerPoint": {
                    "automatic": true,
                    "name": "centre",
                    "x": 0,
                    "y": 0
                  },
                  "customCollisionMask": [
                    [
                      {
                        "x": 20,
                        "y": 13
                      },
                      {
                        "x": 58,
                        "y": 13
                      },
                      {
                        "x": 58,
                        "y": 34
                      },
                      {
                        "x": 20,
                        "y": 34
                      }
                    ]
                  ]
                }
              ]
            }
          ]
        }
      ]
    },
    {
      "assetStoreId": "",
      "bold": false,
      "italic": false,
      "name": "Jugar",
      "smoothed": true,
      "type": "TextObject::Text",
      "underlined": false,
      "variables": [],
      "effects": [],
      "behaviors": [],
      "string": "Jugar",
      "font": "",
      "textAlignment": "left",
      "characterSize": 200,
      "color": {
        "b": 0,
        "g": 0,
        "r": 0
      },
      "content": {
        "bold": false,
        "isOutlineEnabled": false,
        "isShadowEnabled": false,
        "italic": false,
        "outlineColor": "255;255;255",
        "outlineThickness": 2,
        "shadowAngle": 90,
        "shadowBlurRadius": 2,
        "shadowColor": "0;0;0",
        "shadowDistance": 4,
        "shadowOpacity": 127,
        "smoothed": true,
        "underlined": false,
        "text": "Jugar",
        "font": "",
        "textAlignment": "left",
        "characterSize": 200,
        "color": "0;0;0"
      }
    },
    {
      "adaptCollisionMaskAutomatically": true,
      "assetStoreId": "",
      "name": "tierra",
      "type": "Sprite",
      "updateIfNotVisible": false,
      "variables": [],
      "effects": [],
      "behaviors": [],
      "animations": [
        {
          "name": "tierra",
          "useMultipleDirections": false,
          "directions": [
            {
              "looping": false,
              "metadata": "{\"pskl\":{}}",
              "timeBetweenFrames": 0.08,
              "sprites": [
                {
                  "hasCustomCollisionMask": true,
                  "image": "fondo",
                  "points": [],
                  "originPoint": {
                    "name": "origine",
                    "x": 0,
                    "y": 0
                  },
                  "centerPoint": {
                    "automatic": true,
                    "name": "centre",
                    "x": 0,
                    "y": 0
                  },
                  "customCollisionMask": [
                    [
                      {
                        "x": 0,
                        "y": 0
                      },
                      {
                        "x": 64,
                        "y": 0
                      },
                      {
                        "x": 64,
                        "y": 64
                      },
                      {
                        "x": 0,
                        "y": 64
                      }
                    ]
                  ]
                }
              ]
            }
          ]
        }
      ]
    },
    {
      "adaptCollisionMaskAutomatically": true,
      "assetStoreId": "",
      "name": "suelotier",
      "type": "Sprite",
      "updateIfNotVisible": false,
      "variables": [],
      "effects": [],
      "behaviors": [
        {
          "name": "Platform",
          "type": "PlatformBehavior::PlatformBehavior",
          "canBeGrabbed": true,
          "platformType": "NormalPlatform",
          "yGrabOffset": 0
        }
      ],
      "animations": [
        {
          "name": "tierra",
          "useMultipleDirections": false,
          "directions": [
            {
              "looping": false,
              "metadata": "{\"pskl\":{}}",
              "timeBetweenFrames": 0.08,
              "sprites": [
                {
                  "hasCustomCollisionMask": true,
                  "image": "tierra",
                  "points": [],
                  "originPoint": {
                    "name": "origine",
                    "x": 0,
                    "y": 0
                  },
                  "centerPoint": {
                    "automatic": true,
                    "name": "centre",
                    "x": 0,
                    "y": 0
                  },
                  "customCollisionMask": [
                    [
                      {
                        "x": 0,
                        "y": 47
                      },
                      {
                        "x": 64,
                        "y": 47
                      },
                      {
                        "x": 64,
                        "y": 64
                      },
                      {
                        "x": 0,
                        "y": 64
                      }
                    ]
                  ]
                }
              ]
            }
          ]
        }
      ]
    },
    {
      "adaptCollisionMaskAutomatically": true,
      "assetStoreId": "",
      "name": "naveint",
      "type": "Sprite",
      "updateIfNotVisible": false,
      "variables": [],
      "effects": [],
      "behaviors": [],
      "animations": [
        {
          "name": "dentro del cohete",
          "useMultipleDirections": false,
          "directions": [
            {
              "looping": false,
              "metadata": "{\"pskl\":{}}",
              "timeBetweenFrames": 0.08,
              "sprites": [
                {
                  "hasCustomCollisionMask": true,
                  "image": "dentro del cohete2",
                  "points": [],
                  "originPoint": {
                    "name": "origine",
                    "x": 0,
                    "y": 0
                  },
                  "centerPoint": {
                    "automatic": true,
                    "name": "centre",
                    "x": 0,
                    "y": 0
                  },
                  "customCollisionMask": [
                    [
                      {
                        "x": 0,
                        "y": 0
                      },
                      {
                        "x": 1358,
                        "y": 0
                      },
                      {
                        "x": 1358,
                        "y": 806
                      },
                      {
                        "x": 0,
                        "y": 806
                      }
                    ]
                  ]
                }
              ]
            }
          ]
        }
      ]
    },
    {
      "adaptCollisionMaskAutomatically": true,
      "assetStoreId": "",
      "name": "suelonav",
      "type": "Sprite",
      "updateIfNotVisible": false,
      "variables": [],
      "effects": [],
      "behaviors": [
        {
          "name": "Platform",
          "type": "PlatformBehavior::PlatformBehavior",
          "canBeGrabbed": true,
          "platformType": "NormalPlatform",
          "yGrabOffset": 0
        }
      ],
      "animations": [
        {
          "name": "NewSprite8",
          "useMultipleDirections": false,
          "directions": [
            {
              "looping": false,
              "metadata": "{\"pskl\":{}}",
              "timeBetweenFrames": 0.08,
              "sprites": [
                {
                  "hasCustomCollisionMask": true,
                  "image": "NewSprite10",
                  "points": [],
                  "originPoint": {
                    "name": "origine",
                    "x": 0,
                    "y": 0
                  },
                  "centerPoint": {
                    "automatic": true,
                    "name": "centre",
                    "x": 0,
                    "y": 0
                  },
                  "customCollisionMask": [
                    [
                      {
                        "x": 7,
                        "y": 24
                      },
                      {
                        "x": 58,
                        "y": 24
                      },
                      {
                        "x": 58,
                        "y": 41
                      },
                      {
                        "x": 7,
                        "y": 41
                      }
                    ]
                  ]
                }
              ]
            }
          ]
        }
      ]
    },
    {
      "adaptCollisionMaskAutomatically": true,
      "assetStoreId": "",
      "name": "marte_",
      "type": "Sprite",
      "updateIfNotVisible": false,
      "variables": [],
      "effects": [],
      "behaviors": [],
      "animations": [
        {
          "name": "marte",
          "useMultipleDirections": false,
          "directions": [
            {
              "looping": false,
              "metadata": "{\"pskl\":{}}",
              "timeBetweenFrames": 0.08,
              "sprites": [
                {
                  "hasCustomCollisionMask": true,
                  "image": "marte",
                  "points": [],
                  "originPoint": {
                    "name": "origine",
                    "x": 0,
                    "y": 0
                  },
                  "centerPoint": {
                    "automatic": true,
                    "name": "centre",
                    "x": 0,
                    "y": 0
                  },
                  "customCollisionMask": [
                    [
                      {
                        "x": 0,
                        "y": 0
                      },
                      {
                        "x": 64,
                        "y": 0
                      },
                      {
                        "x": 64,
                        "y": 64
                      },
                      {
                        "x": 0,
                        "y": 64
                      }
                    ]
                  ]
                }
              ]
            }
          ]
        }
      ]
    }
  ],
  "objectsFolderStructure": {
    "folderName": "__ROOT",
    "children": [
      {
        "objectName": "tierra_inicio"
      },
      {
        "objectName": "marte_"
      },
      {
        "objectName": "naveint"
      },
      {
        "objectName": "suelonav"
      },
      {
        "objectName": "tierra"
      },
      {
        "objectName": "suelotier"
      },
      {
        "objectName": "Laika"
      },
      {
        "objectName": "Enemigo"
      },
      {
        "objectName": "Estrella"
      },
      {
        "objectName": "cohete"
      },
      {
        "objectName": "tarjeta"
      },
      {
        "objectName": "piedra"
      },
      {
        "objectName": "laikanav"
      },
      {
        "objectName": "text"
      },
      {
        "objectName": "Jugar"
      }
    ]
  },
  "objectsGroups": [],
  "variables": [],
  "layouts": [
    {
      "b": 209,
      "disableInputWhenNotFocused": true,
      "mangledName": "inicio",
      "name": "inicio",
      "r": 209,
      "standardSortMethod": true,
      "stopSoundsOnStartup": true,
      "title": "",
      "v": 209,
      "uiSettings": {
        "grid": false,
        "gridType": "rectangular",
        "gridWidth": 32,
        "gridHeight": 32,
        "gridOffsetX": 0,
        "gridOffsetY": 0,
        "gridColor": 10401023,
        "gridAlpha": 0.8,
        "snap": false,
        "zoomFactor": 0.6040838749988877,
        "windowMask": false
      },
      "objectsGroups": [],
      "variables": [],
      "instances": [
        {
          "angle": 0,
          "customSize": true,
          "depth": 1,
          "height": 887,
          "keepRatio": true,
          "layer": "",
          "name": "tierra_inicio",
          "persistentUuid": "0f62bbcd-7c27-4685-ba65-3bafdad8df07",
          "width": 1282,
          "x": -3,
          "y": -2,
          "zOrder": -1,
          "numberProperties": [],
          "stringProperties": [],
          "initialVariables": []
        },
        {
          "angle": 0,
          "customSize": true,
          "depth": 1,
          "height": 538,
          "keepRatio": true,
          "layer": "",
          "name": "laikanav",
          "persistentUuid": "fd92ee77-3f95-45fa-afab-c551f7a9a9a4",
          "width": 627,
          "x": 327,
          "y": -8,
          "zOrder": 0,
          "numberProperties": [],
          "stringProperties": [],
          "initialVariables": []
        },
        {
          "angle": 0,
          "customSize": true,
          "depth": 1,
          "height": 789,
          "keepRatio": true,
          "layer": "",
          "name": "text",
          "persistentUuid": "0d6a0774-1f29-461d-8f80-366c9754eac3",
          "width": 1022,
          "x": 8,
          "y": 266,
          "zOrder": 1,
          "numberProperties": [],
          "stringProperties": [],
          "initialVariables": []
        },
        {
          "angle": 0,
          "customSize": false,
          "height": 0,
          "keepRatio": true,
          "layer": "",
          "name": "Jugar",
          "persistentUuid": "36cc41bc-cfea-4073-82c8-6792ac5c45ca",
          "width": 0,
          "x": 370,
          "y": 433,
          "zOrder": 2,
          "numberProperties": [],
          "stringProperties": [],
          "initialVariables": []
        }
      ],
      "objects": [],
      "objectsFolderStructure": {
        "folderName": "__ROOT"
      },
      "events": [
        {
          "type": "BuiltinCommonInstructions::Standard",
          "conditions": [],
          "actions": [
            {
              "type": {
                "value": "Scene"
              },
              "parameters": [
                "",
                "\"inicio\"",
                ""
              ]
            }
          ]
        },
        {
          "type": "BuiltinCommonInstructions::Standard",
          "conditions": [
            {
              "type": {
                "value": "SourisSurObjet"
              },
              "parameters": [
                "Jugar",
                "",
                "",
                ""
              ]
            }
          ],
          "actions": [
            {
              "type": {
                "value": "Scene"
              },
              "parameters": [
                "",
                "\"nivel 1\"",
                ""
              ]
            }
          ]
        }
      ],
      "layers": [
        {
          "ambientLightColorB": 200,
          "ambientLightColorG": 200,
          "ambientLightColorR": 200,
          "camera3DFarPlaneDistance": 10000,
          "camera3DFieldOfView": 45,
          "camera3DNearPlaneDistance": 3,
          "cameraType": "",
          "followBaseLayerCamera": false,
          "isLightingLayer": false,
          "isLocked": false,
          "name": "",
          "renderingType": "",
          "visibility": true,
          "cameras": [
            {
              "defaultSize": true,
              "defaultViewport": true,
              "height": 0,
              "viewportBottom": 1,
              "viewportLeft": 0,
              "viewportRight": 1,
              "viewportTop": 0,
              "width": 0
            }
          ],
          "effects": [
            {
              "effectType": "Scene3D::HemisphereLight",
              "name": "3D Light",
              "doubleParameters": {
                "elevation": 45,
                "intensity": 1,
                "rotation": 0
              },
              "stringParameters": {
                "groundColor": "64;64;64",
                "skyColor": "255;255;255",
                "top": "Y-"
              },
              "booleanParameters": {}
            }
          ]
        }
      ],
      "behaviorsSharedData": [
        {
          "name": "Animation",
          "type": "AnimatableCapability::AnimatableBehavior"
        },
        {
          "name": "Effect",
          "type": "EffectCapability::EffectBehavior"
        },
        {
          "name": "Flippable",
          "type": "FlippableCapability::FlippableBehavior"
        },
        {
          "name": "Opacity",
          "type": "OpacityCapability::OpacityBehavior"
        },
        {
          "name": "Platform",
          "type": "PlatformBehavior::PlatformBehavior"
        },
        {
          "name": "PlatformerObject",
          "type": "PlatformBehavior::PlatformerObjectBehavior"
        },
        {
          "name": "Resizable",
          "type": "ResizableCapability::ResizableBehavior"
        },
        {
          "name": "Scale",
          "type": "ScalableCapability::ScalableBehavior"
        },
        {
          "name": "Text",
          "type": "TextContainerCapability::TextContainerBehavior"
        },
        {
          "name": "TopDownMovement",
          "type": "TopDownMovementBehavior::TopDownMovementBehavior"
        }
      ]
    },
    {
      "b": 209,
      "disableInputWhenNotFocused": true,
      "mangledName": "nivel_321",
      "name": "nivel 1",
      "r": 209,
      "standardSortMethod": true,
      "stopSoundsOnStartup": true,
      "title": "",
      "v": 209,
      "uiSettings": {
        "grid": false,
        "gridType": "rectangular",
        "gridWidth": 32,
        "gridHeight": 32,
        "gridOffsetX": 0,
        "gridOffsetY": 0,
        "gridColor": 10401023,
        "gridAlpha": 0.8,
        "snap": false,
        "zoomFactor": 0.5117784035210186,
        "windowMask": false
      },
      "objectsGroups": [],
      "variables": [],
      "instances": [
        {
          "angle": 0,
          "customSize": true,
          "depth": 1,
          "height": 1133,
          "keepRatio": true,
          "layer": "",
          "name": "tierra",
          "persistentUuid": "2f1e115e-54fc-4c03-a70b-ede427eaa5c0",
          "width": 2274,
          "x": -632,
          "y": -120,
          "zOrder": 1,
          "numberProperties": [],
          "stringProperties": [],
          "initialVariables": []
        },
        {
          "angle": 0,
          "customSize": true,
          "depth": 1,
          "height": 383,
          "keepRatio": true,
          "layer": "",
          "name": "text",
          "persistentUuid": "15f9c3fe-cd80-4ea4-95c8-75ef29725df2",
          "width": 783,
          "x": -165,
          "y": -39,
          "zOrder": 2,
          "numberProperties": [],
          "stringProperties": [],
          "initialVariables": []
        },
        {
          "angle": 0,
          "customSize": true,
          "depth": 1,
          "height": 445,
          "keepRatio": true,
          "layer": "",
          "name": "Laika",
          "persistentUuid": "8634ef0a-f9fc-4757-8e45-a6712727d7a4",
          "width": 498,
          "x": -253,
          "y": 359,
          "zOrder": 6,
          "numberProperties": [],
          "stringProperties": [],
          "initialVariables": []
        },
        {
          "angle": 0,
          "customSize": true,
          "depth": 1,
          "height": 264,
          "keepRatio": true,
          "layer": "",
          "name": "tarjeta",
          "persistentUuid": "777f7f78-c348-4a13-b5d5-4eb3cc860b2e",
          "width": 202,
          "x": 528,
          "y": 424,
          "zOrder": 4,
          "numberProperties": [],
          "stringProperties": [],
          "initialVariables": []
        },
        {
          "angle": 0,
          "customSize": true,
          "depth": 1,
          "height": 670,
          "keepRatio": true,
          "layer": "",
          "name": "cohete",
          "persistentUuid": "560ed727-63c4-4edb-b8e5-563664fc0aa8",
          "width": 832,
          "x": 729,
          "y": 176,
          "zOrder": 5,
          "numberProperties": [],
          "stringProperties": [],
          "initialVariables": []
        },
        {
          "angle": 0,
          "customSize": false,
          "height": 0,
          "keepRatio": true,
          "layer": "",
          "name": "NewText",
          "persistentUuid": "f80b3927-dbf2-4cf5-a3e3-dc59085278d1",
          "width": 0,
          "x": 131,
          "y": 62,
          "zOrder": 6,
          "numberProperties": [],
          "stringProperties": [],
          "initialVariables": []
        },
        {
          "angle": 0,
          "customSize": true,
          "depth": 1,
          "height": 1417,
          "keepRatio": true,
          "layer": "",
          "name": "suelotier",
          "persistentUuid": "785352a6-ab3c-4b9f-ba29-8402d88b3411",
          "width": 2322,
          "x": -630,
          "y": -438,
          "zOrder": 2,
          "numberProperties": [],
          "stringProperties": [],
          "initialVariables": []
        }
      ],
      "objects": [
        {
          "assetStoreId": "",
          "bold": false,
          "italic": false,
          "name": "NewText",
          "smoothed": true,
          "type": "TextObject::Text",
          "underlined": false,
          "variables": [],
          "effects": [],
          "behaviors": [],
          "string": "a - d / ⭠ ⭢",
          "font": "",
          "textAlignment": "left",
          "characterSize": 75,
          "color": {
            "b": 0,
            "g": 0,
            "r": 0
          },
          "content": {
            "bold": false,
            "isOutlineEnabled": false,
            "isShadowEnabled": false,
            "italic": false,
            "outlineColor": "255;255;255",
            "outlineThickness": 2,
            "shadowAngle": 90,
            "shadowBlurRadius": 2,
            "shadowColor": "0;0;0",
            "shadowDistance": 4,
            "shadowOpacity": 127,
            "smoothed": true,
            "underlined": false,
            "text": "a - d / ⭠ ⭢",
            "font": "",
            "textAlignment": "left",
            "characterSize": 75,
            "color": "0;0;0"
          }
        }
      ],
      "objectsFolderStructure": {
        "folderName": "__ROOT",
        "children": [
          {
            "objectName": "NewText"
          }
        ]
      },
      "events": [
        {
          "type": "BuiltinCommonInstructions::Standard",
          "conditions": [],
          "actions": [
            {
              "type": {
                "value": "CentreCamera"
              },
              "parameters": [
                "",
                "Laika",
                "",
                "",
                ""
              ]
            }
          ]
        },
        {
          "type": "BuiltinCommonInstructions::Standard",
          "conditions": [
            {
              "type": {
                "value": "KeyPressed"
              },
              "parameters": [
                "",
                "d"
              ]
            }
          ],
          "actions": [
            {
              "type": {
                "value": "TopDownMovementBehavior::SimulateRightKey"
              },
              "parameters": [
                "Laika",
                "TopDownMovement"
              ]
            }
          ]
        },
        {
          "type": "BuiltinCommonInstructions::Standard",
          "conditions": [
            {
              "type": {
                "value": "KeyPressed"
              },
              "parameters": [
                "",
                "a"
              ]
            }
          ],
          "actions": [
            {
              "type": {
                "value": "TopDownMovementBehavior::SimulateLeftKey"
              },
              "parameters": [
                "Laika",
                "TopDownMovement"
              ]
            }
          ]
        },
        {
          "type": "BuiltinCommonInstructions::Standard",
          "conditions": [
            {
              "type": {
                "value": "BuiltinCommonInstructions::Or"
              },
              "parameters": [],
              "subInstructions": [
                {
                  "type": {
                    "value": "KeyPressed"
                  },
                  "parameters": [
                    "",
                    "Space"
                  ]
                },
                {
                  "type": {
                    "value": "KeyPressed"
                  },
                  "parameters": [
                    "",
                    "w"
                  ]
                }
              ]
            }
          ],
          "actions": [
            {
              "type": {
                "value": "PlatformBehavior::SimulateJumpKey"
              },
              "parameters": [
                "Laika",
                "PlatformerObject"
              ]
            },
            {
              "type": {
                "value": "PlaySound"
              },
              "parameters": [
                "",
                "salto.mp3.wav",
                "",
                "20",
                ""
              ]
            }
          ]
        },
        {
          "type": "BuiltinCommonInstructions::Standard",
          "conditions": [
            {
              "type": {
                "value": "CollisionNP"
              },
              "parameters": [
                "Laika",
                "tarjeta",
                "",
                "",
                ""
              ]
            }
          ],
          "actions": [
            {
              "type": {
                "value": "Delete"
              },
              "parameters": [
                "tarjeta",
                ""
              ]
            },
            {
              "type": {
                "value": "PlaySound"
              },
              "parameters": [
                "",
                "agarrar.mp3.wav",
                "",
                "50",
                ""
              ]
            }
          ]
        },
        {
          "type": "BuiltinCommonInstructions::Standard",
          "conditions": [
            {
              "type": {
                "value": "BuiltinCommonInstructions::And"
              },
              "parameters": [],
              "subInstructions": [
                {
                  "type": {
                    "value": "CollisionNP"
                  },
                  "parameters": [
                    "Laika",
                    "cohete",
                    "",
                    "",
                    ""
                  ]
                }
              ]
            }
          ],
          "actions": [
            {
              "type": {
                "value": "Scene"
              },
              "parameters": [
                "",
                "\"1 pt 2\"",
                ""
              ]
            }
          ]
        },
        {
          "type": "BuiltinCommonInstructions::Standard",
          "conditions": [],
          "actions": []
        }
      ],
      "layers": [
        {
          "ambientLightColorB": 200,
          "ambientLightColorG": 200,
          "ambientLightColorR": 200,
          "camera3DFarPlaneDistance": 10000,
          "camera3DFieldOfView": 45,
          "camera3DNearPlaneDistance": 3,
          "cameraType": "",
          "followBaseLayerCamera": false,
          "isLightingLayer": false,
          "isLocked": false,
          "name": "",
          "renderingType": "",
          "visibility": true,
          "cameras": [
            {
              "defaultSize": true,
              "defaultViewport": true,
              "height": 0,
              "viewportBottom": 1,
              "viewportLeft": 0,
              "viewportRight": 1,
              "viewportTop": 0,
              "width": 0
            }
          ],
          "effects": [
            {
              "effectType": "Scene3D::HemisphereLight",
              "name": "3D Light",
              "doubleParameters": {
                "elevation": 45,
                "intensity": 1,
                "rotation": 0
              },
              "stringParameters": {
                "groundColor": "64;64;64",
                "skyColor": "255;255;255",
                "top": "Y-"
              },
              "booleanParameters": {}
            }
          ]
        }
      ],
      "behaviorsSharedData": [
        {
          "name": "Animation",
          "type": "AnimatableCapability::AnimatableBehavior"
        },
        {
          "name": "Effect",
          "type": "EffectCapability::EffectBehavior"
        },
        {
          "name": "Flippable",
          "type": "FlippableCapability::FlippableBehavior"
        },
        {
          "name": "Opacity",
          "type": "OpacityCapability::OpacityBehavior"
        },
        {
          "name": "Platform",
          "type": "PlatformBehavior::PlatformBehavior"
        },
        {
          "name": "PlatformerObject",
          "type": "PlatformBehavior::PlatformerObjectBehavior"
        },
        {
          "name": "Resizable",
          "type": "ResizableCapability::ResizableBehavior"
        },
        {
          "name": "Scale",
          "type": "ScalableCapability::ScalableBehavior"
        },
        {
          "name": "Text",
          "type": "TextContainerCapability::TextContainerBehavior"
        },
        {
          "name": "TopDownMovement",
          "type": "TopDownMovementBehavior::TopDownMovementBehavior"
        }
      ]
    },
    {
      "b": 209,
      "disableInputWhenNotFocused": true,
      "mangledName": "_49_32pt_322",
      "name": "1 pt 2",
      "r": 209,
      "standardSortMethod": true,
      "stopSoundsOnStartup": true,
      "title": "",
      "v": 209,
      "uiSettings": {
        "grid": false,
        "gridType": "rectangular",
        "gridWidth": 32,
        "gridHeight": 32,
        "gridOffsetX": 0,
        "gridOffsetY": 0,
        "gridColor": 10401023,
        "gridAlpha": 0.8,
        "snap": false,
        "zoomFactor": 0.546875,
        "windowMask": false
      },
      "objectsGroups": [],
      "variables": [],
      "instances": [
        {
          "angle": 0,
          "customSize": true,
          "depth": 1,
          "height": 454,
          "keepRatio": true,
          "layer": "",
          "name": "Laika",
          "persistentUuid": "dc17189e-937f-45d3-aa73-6e79bf732707",
          "width": 491,
          "x": 328,
          "y": 170,
          "zOrder": 2,
          "numberProperties": [],
          "stringProperties": [],
          "initialVariables": []
        },
        {
          "angle": 0,
          "customSize": false,
          "height": 0,
          "keepRatio": true,
          "layer": "",
          "name": "naveint",
          "persistentUuid": "7b3b8d02-52b7-44bc-ac6e-08c1c2cd445f",
          "width": 0,
          "x": -4,
          "y": -40,
          "zOrder": 1,
          "numberProperties": [],
          "stringProperties": [],
          "initialVariables": []
        },
        {
          "angle": 0,
          "customSize": true,
          "depth": 1,
          "height": 523,
          "keepRatio": true,
          "layer": "",
          "name": "suelonav",
          "persistentUuid": "05100ede-befc-4f81-a8c7-7ff9f48b223a",
          "width": 1748,
          "x": -203,
          "y": 415,
          "zOrder": 3,
          "numberProperties": [],
          "stringProperties": [],
          "initialVariables": []
        }
      ],
      "objects": [],
      "objectsFolderStructure": {
        "folderName": "__ROOT"
      },
      "events": [
        {
          "type": "BuiltinCommonInstructions::Standard",
          "conditions": [],
          "actions": [
            {
              "type": {
                "value": "CentreCamera"
              },
              "parameters": [
                "",
                "Laika",
                "",
                "",
                ""
              ]
            }
          ]
        },
        {
          "type": "BuiltinCommonInstructions::Standard",
          "conditions": [
            {
              "type": {
                "value": "KeyPressed"
              },
              "parameters": [
                "",
                "a"
              ]
            }
          ],
          "actions": [
            {
              "type": {
                "value": "TopDownMovementBehavior::SimulateLeftKey"
              },
              "parameters": [
                "Laika",
                "TopDownMovement"
              ]
            }
          ]
        },
        {
          "type": "BuiltinCommonInstructions::Standard",
          "conditions": [
            {
              "type": {
                "value": "KeyPressed"
              },
              "parameters": [
                "",
                "d"
              ]
            }
          ],
          "actions": [
            {
              "type": {
                "value": "TopDownMovementBehavior::SimulateRightKey"
              },
              "parameters": [
                "Laika",
                "TopDownMovement"
              ]
            }
          ]
        },
        {
          "type": "BuiltinCommonInstructions::Standard",
          "conditions": [
            {
              "type": {
                "value": "BuiltinCommonInstructions::Or"
              },
              "parameters": [],
              "subInstructions": [
                {
                  "type": {
                    "value": "KeyPressed"
                  },
                  "parameters": [
                    "",
                    "Space"
                  ]
                },
                {
                  "type": {
                    "value": "KeyPressed"
                  },
                  "parameters": [
                    "",
                    "w"
                  ]
                }
              ]
            }
          ],
          "actions": [
            {
              "type": {
                "value": "PlatformBehavior::SimulateJumpKey"
              },
              "parameters": [
                "Laika",
                "PlatformerObject"
              ]
            },
            {
              "type": {
                "value": "PlaySound"
              },
              "parameters": [
                "",
                "salto.mp3.wav",
                "",
                "20",
                ""
              ]
            }
          ]
        },
        {
          "type": "BuiltinCommonInstructions::Standard",
          "conditions": [],
          "actions": []
        }
      ],
      "layers": [
        {
          "ambientLightColorB": 200,
          "ambientLightColorG": 200,
          "ambientLightColorR": 200,
          "camera3DFarPlaneDistance": 10000,
          "camera3DFieldOfView": 45,
          "camera3DNearPlaneDistance": 3,
          "cameraType": "",
          "followBaseLayerCamera": false,
          "isLightingLayer": false,
          "isLocked": false,
          "name": "",
          "renderingType": "",
          "visibility": true,
          "cameras": [
            {
              "defaultSize": true,
              "defaultViewport": true,
              "height": 0,
              "viewportBottom": 1,
              "viewportLeft": 0,
              "viewportRight": 1,
              "viewportTop": 0,
              "width": 0
            }
          ],
          "effects": [
            {
              "effectType": "Scene3D::HemisphereLight",
              "name": "3D Light",
              "doubleParameters": {
                "elevation": 45,
                "intensity": 1,
                "rotation": 0
              },
              "stringParameters": {
                "groundColor": "64;64;64",
                "skyColor": "255;255;255",
                "top": "Y-"
              },
              "booleanParameters": {}
            }
          ]
        }
      ],
      "behaviorsSharedData": [
        {
          "name": "Animation",
          "type": "AnimatableCapability::AnimatableBehavior"
        },
        {
          "name": "Effect",
          "type": "EffectCapability::EffectBehavior"
        },
        {
          "name": "Flippable",
          "type": "FlippableCapability::FlippableBehavior"
        },
        {
          "name": "Opacity",
          "type": "OpacityCapability::OpacityBehavior"
        },
        {
          "name": "Platform",
          "type": "PlatformBehavior::PlatformBehavior"
        },
        {
          "name": "PlatformerObject",
          "type": "PlatformBehavior::PlatformerObjectBehavior"
        },
        {
          "name": "Resizable",
          "type": "ResizableCapability::ResizableBehavior"
        },
        {
          "name": "Scale",
          "type": "ScalableCapability::ScalableBehavior"
        },
        {
          "name": "Text",
          "type": "TextContainerCapability::TextContainerBehavior"
        },
        {
          "name": "TopDownMovement",
          "type": "TopDownMovementBehavior::TopDownMovementBehavior"
        }
      ]
    }
  ],
  "externalEvents": [],
  "eventsFunctionsExtensions": [],
  "externalLayouts": [],
  "externalSourceFiles": []
}